billomapy/__init__.py
billomapy/billomapy.py
billomapy/damn_flood_billomapy.py
billomapy/resources.py
billomapy-2.5.1.dist-info/DESCRIPTION.rst
billomapy-2.5.1.dist-info/METADATA
billomapy-2.5.1.dist-info/RECORD
billomapy-2.5.1.dist-info/WHEEL
billomapy-2.5.1.dist-info/metadata.json
billomapy-2.5.1.dist-info/top_level.txt
